README.rst
setup.cfg
setup.py
apistar_mongoengine/__init__.py
apistar_mongoengine/components.py
apistar_mongoengine/models.py
apistar_mongoengine/pagination.py
apistar_mongoengine/types.py
apistar_mongoengine.egg-info/PKG-INFO
apistar_mongoengine.egg-info/SOURCES.txt
apistar_mongoengine.egg-info/dependency_links.txt
apistar_mongoengine.egg-info/not-zip-safe
apistar_mongoengine.egg-info/requires.txt
apistar_mongoengine.egg-info/top_level.txt